calphy/__init__.py
calphy/alchemy.py
calphy/clitools.py
calphy/composition_transformation.py
calphy/errors.py
calphy/helpers.py
calphy/input.py
calphy/integrators.py
calphy/kernel.py
calphy/liquid.py
calphy/phase.py
calphy/phase_diagram.py
calphy/postprocessing.py
calphy/queuekernel.py
calphy/routines.py
calphy/scheduler.py
calphy/solid.py
calphy/splines.py
calphy/utils.py
calphy-1.4.6.dist-info/licenses/LICENSE
calphy-1.4.6.dist-info/METADATA
calphy-1.4.6.dist-info/WHEEL
calphy-1.4.6.dist-info/entry_points.txt
calphy-1.4.6.dist-info/top_level.txt
calphy-1.4.6.dist-info/RECORD
