Metadata-Version: 2.4
Name: calphy
Version: 1.4.6
Summary: free energy calculation for python
Home-page: https://github.com/ICAMS/calphy
Author: Sarath Menon, Yury Lysogorskiy, Ralf Drautz
Author-email: sarathmenon@mailbox.org
License: GNU General Public License v3
Keywords: calphy
Classifier: License :: OSI Approved :: GNU General Public License v3 (GPLv3)
Classifier: Natural Language :: English
Classifier: Programming Language :: Python :: 3.10
Classifier: Programming Language :: Python :: 3.11
Requires-Python: >=3.8
License-File: LICENSE
Requires-Dist: matplotlib
Requires-Dist: pytest
Requires-Dist: pyyaml
Requires-Dist: mendeleev
Requires-Dist: tqdm
Requires-Dist: scipy
Requires-Dist: pydantic
Requires-Dist: pyscal3
Dynamic: author
Dynamic: author-email
Dynamic: classifier
Dynamic: description
Dynamic: description-content-type
Dynamic: home-page
Dynamic: keywords
Dynamic: license
Dynamic: license-file
Dynamic: requires-dist
Dynamic: requires-python
Dynamic: summary
